Topsis_bhavkirat_101803020/__init__.py
Topsis_bhavkirat_101803020-1.0.0.dist-info/METADATA
Topsis_bhavkirat_101803020-1.0.0.dist-info/WHEEL
Topsis_bhavkirat_101803020-1.0.0.dist-info/top_level.txt
Topsis_bhavkirat_101803020-1.0.0.dist-info/RECORD
