Metadata-Version: 2.1
Name: Topsis-bhavkirat-101803020
Version: 1.0.0
Summary: Get Topsis Rank of a DataSet
Home-page: UNKNOWN
Author: Bhavkirat Singh
Author-email: bhavkirats@gmail.com
License: UNKNOWN
Platform: UNKNOWN
Classifier: Programming Language :: Python :: 3
Classifier: License :: OSI Approved :: MIT License
Classifier: Operating System :: OS Independent
